sft_dpo_qlora/__init__.py
sft_dpo_qlora/configDPO.py
sft_dpo_qlora/configSFT.py
sft_dpo_qlora/trainerDPO.py
sft_dpo_qlora/trainerSFT.py
sft_dpo_qlora-0.1.4.dist-info/LICENSE
sft_dpo_qlora-0.1.4.dist-info/METADATA
sft_dpo_qlora-0.1.4.dist-info/WHEEL
sft_dpo_qlora-0.1.4.dist-info/top_level.txt
sft_dpo_qlora-0.1.4.dist-info/RECORD
