Metadata-Version: 2.1
Name: sft_dpo_qlora
Version: 0.1.4
Summary: SFT-DPO-QLora Trainer Package
Home-page: https://github.com/Sherma-ThangamS/SFT-DPO-QLora
Author: Sherma Thangam S
Author-email: sshermathangam@gmail.com
Keywords: sft dpo qlora trainer
Classifier: Development Status :: 3 - Alpha
Classifier: Intended Audience :: Developers
Classifier: Programming Language :: Python :: 3
Classifier: License :: OSI Approved :: MIT License
Classifier: Operating System :: OS Independent
Requires-Python: >=3.9
License-File: LICENSE
Requires-Dist: torch
Requires-Dist: datasets
Requires-Dist: peft
Requires-Dist: transformers
Requires-Dist: trl
Requires-Dist: bitsandbytes
Requires-Dist: auto-gptq
Requires-Dist: optimum
Requires-Dist: einops
